MANIFEST.in
README.md
requirements.txt
setup.cfg
setup.py
versioneer.py
botcity/utils/__init__.py
botcity/utils/_version.py
botcity/utils/parser/__init__.py
botcity/utils/parser/string.py
botcity/utils/tests/__init__.py
botcity/utils/tests/parser/__init__.py
botcity/utils/tests/parser/test_string_parser.py
botcity_utils.egg-info/PKG-INFO
botcity_utils.egg-info/SOURCES.txt
botcity_utils.egg-info/dependency_links.txt
botcity_utils.egg-info/top_level.txt