Metadata-Version: 2.1
Name: botcity-utils
Version: 0.1.2
Summary: UNKNOWN
Home-page: https://bitbucket.org/botcitydev/bot-utils-python.git
License: UNKNOWN
Platform: UNKNOWN
Requires-Python: >=3.7
